{"project_info":{"project_id":"mytube-eca9a","project_number":"10247328491","name":"MyTube"},"client":[{"client_info":{"mobilesdk_app_id":"1:10247328491:android:cd04c0379d7c14da","client_id":"android:com.example.nmendiratta.mytube","client_type":1,"android_client_info":{"package_name":"com.example.nmendiratta.mytube"}},"oauth_client":[{"client_id":"10247328491-h8ai70sdf0m838mlb8005bdeko81uciq.apps.googleusercontent.com","client_type":1,"android_info":{"package_name":"com.example.nmendiratta.mytube","certificate_hash":"93472462fe1d2114932b93b5194247c58d4ba613"}}],"api_key":[],"services":{"analytics_service":{"status":1},"cloud_messaging_service":{"status":1,"apns_config":[]},"appinvite_service":{"status":1,"other_platform_oauth_client":[]},"google_signin_service":{"status":2},"ads_service":{"status":1}}}],"client_info":[],"ARTIFACT_VERSION":"1"}